pypp_python/__init__.py
pypp_python/configclass.py
pypp_python/conversions.py
pypp_python/custom_types.py
pypp_python/dict_get.py
pypp_python/exceptionclass.py
pypp_python/lists.py
pypp_python/math.py
pypp_python/nones.py
pypp_python/ownership.py
pypp_python/resources.py
pypp_python/strings.py
pypp_python/tuple_get.py
pypp_python/union.py
pypp_python/interfaces/__init__.py
pypp_python/stl/__init__.py
pypp_python/stl/time/__init__.py
pypp_python-0.0.1.dist-info/METADATA
pypp_python-0.0.1.dist-info/WHEEL
pypp_python-0.0.1.dist-info/licenses/LICENSE
pypp_python-0.0.1.dist-info/RECORD
