Metadata-Version: 2.4
Name: pypp-python
Version: 0.0.1
Summary: contains necessary python code for Py++ projects
Project-URL: Homepage, https://github.com/curtispuetz/pypp-python
Author-email: Curtis Puetz <pypp.main@yahoo.com>
License: MIT
License-File: LICENSE
Requires-Python: >=3.13
